sdmx/__init__.py
sdmx/client.py
sdmx/compare.py
sdmx/dictlike.py
sdmx/exceptions.py
sdmx/experimental.py
sdmx/message.py
sdmx/py.typed
sdmx/session.py
sdmx/sources.json
sdmx/tools.py
sdmx/types.py
sdmx/urn.py
sdmx/convert/__init__.py
sdmx/convert/common.py
sdmx/convert/pandas.py
sdmx/format/__init__.py
sdmx/format/common.py
sdmx/format/json.py
sdmx/format/protobuf_pb2.py
sdmx/format/csv/__init__.py
sdmx/format/csv/common.py
sdmx/format/csv/v1.py
sdmx/format/csv/v2.py
sdmx/format/xml/__init__.py
sdmx/format/xml/common.py
sdmx/format/xml/v21.py
sdmx/format/xml/v30.py
sdmx/model/__init__.py
sdmx/model/common.py
sdmx/model/internationalstring.py
sdmx/model/v21.py
sdmx/model/v30.py
sdmx/model/version.py
sdmx/reader/__init__.py
sdmx/reader/base.py
sdmx/reader/csv.py
sdmx/reader/json.py
sdmx/reader/xml/__init__.py
sdmx/reader/xml/common.py
sdmx/reader/xml/v21.py
sdmx/reader/xml/v30.py
sdmx/rest/__init__.py
sdmx/rest/common.py
sdmx/rest/v21.py
sdmx/rest/v30.py
sdmx/source/__init__.py
sdmx/source/abs.py
sdmx/source/abs_json.py
sdmx/source/bbk.py
sdmx/source/comp.py
sdmx/source/empl.py
sdmx/source/estat.py
sdmx/source/estat3.py
sdmx/source/estat_comext.py
sdmx/source/grow.py
sdmx/source/imf_data.py
sdmx/source/imf_data3.py
sdmx/source/insee.py
sdmx/source/istat.py
sdmx/source/lsd.py
sdmx/source/oecd.py
sdmx/source/oecd_json.py
sdmx/source/sgr.py
sdmx/source/wb.py
sdmx/source/wb_wdi.py
sdmx/testing/__init__.py
sdmx/testing/data.py
sdmx/testing/report.py
sdmx/tests/__init__.py
sdmx/tests/conftest.py
sdmx/tests/test_client.py
sdmx/tests/test_compare.py
sdmx/tests/test_compat.py
sdmx/tests/test_dataset.py
sdmx/tests/test_dataset_bare.py
sdmx/tests/test_dataset_ss.py
sdmx/tests/test_docs.py
sdmx/tests/test_dsd.py
sdmx/tests/test_experimental.py
sdmx/tests/test_format.py
sdmx/tests/test_insee.py
sdmx/tests/test_message.py
sdmx/tests/test_model.py
sdmx/tests/test_performance.py
sdmx/tests/test_reader.py
sdmx/tests/test_rest.py
sdmx/tests/test_session.py
sdmx/tests/test_source.py
sdmx1-2.25.0.dist-info/METADATA
sdmx1-2.25.0.dist-info/WHEEL
sdmx1-2.25.0.dist-info/licenses/LICENSE
sdmx1-2.25.0.dist-info/RECORD
