Metadata-Version: 2.4
Name: sdmx1
Version: 2.25.0
Summary: Statistical Data and Metadata eXchange (SDMX)
Project-URL: Homepage, https://github.com/khaeru/sdmx
Project-URL: Repository, https://github.com/khaeru/sdmx
Project-URL: Documentation, https://sdmx1.readthedocs.io/en/latest
Author: SDMX Python developers
Maintainer-email: Paul Natsuo Kishimoto <mail@paul.kishimoto.name>
License-File: LICENSE
Keywords: SDMX,data,economics,pandas,science,statistics
Classifier: Intended Audience :: Developers
Classifier: Intended Audience :: Financial and Insurance Industry
Classifier: Intended Audience :: Science/Research
Classifier: License :: OSI Approved :: Apache Software License
Classifier: Operating System :: OS Independent
Classifier: Programming Language :: Python
Classifier: Programming Language :: Python :: 3
Classifier: Programming Language :: Python :: 3.10
Classifier: Programming Language :: Python :: 3.11
Classifier: Programming Language :: Python :: 3.12
Classifier: Programming Language :: Python :: 3.13
Classifier: Programming Language :: Python :: 3.14
Classifier: Topic :: Scientific/Engineering
Classifier: Topic :: Scientific/Engineering :: Information Analysis
Requires-Python: >=3.10
Requires-Dist: lxml>=3.6
Requires-Dist: pandas>=1.0
Requires-Dist: platformdirs>=4.1
Requires-Dist: python-dateutil
Requires-Dist: requests>=2.7
Provides-Extra: cache
Requires-Dist: requests-cache; extra == 'cache'
Provides-Extra: docs
Requires-Dist: furo; extra == 'docs'
Requires-Dist: ipython; extra == 'docs'
Requires-Dist: sphinx>=8; extra == 'docs'
Provides-Extra: tests
Requires-Dist: filelock; extra == 'tests'
Requires-Dist: gitpython; extra == 'tests'
Requires-Dist: jinja2; extra == 'tests'
Requires-Dist: pytest-cov; extra == 'tests'
Requires-Dist: pytest-rerunfailures; extra == 'tests'
Requires-Dist: pytest-xdist; extra == 'tests'
Requires-Dist: pytest>=5; extra == 'tests'
Requires-Dist: requests-cache; extra == 'tests'
Requires-Dist: responses; extra == 'tests'
